LICENSE
MANIFEST.in
README.md
setup.py
bccd/__init__.py
bccd/__main__.py
bccd.egg-info/PKG-INFO
bccd.egg-info/SOURCES.txt
bccd.egg-info/dependency_links.txt
bccd.egg-info/entry_points.txt
bccd.egg-info/requires.txt
bccd.egg-info/top_level.txt
bccd/backend/PltTracker.py
bccd/backend/Target.py
bccd/backend/__init__.py
bccd/backend/colors.py
bccd/backend/fits.py
bccd/backend/functions.py
bccd/gui/__init__.py
bccd/gui/bccd.py
bccd/gui/fits_tab.py
bccd/gui/popup_target.py
bccd/images/icon.gif