Metadata-Version: 2.1
Name: bccd
Version: 2.7.0
Summary: B-NMR/B-NQR Beamspot Image Viewer and Analysis
Home-page: https://github.com/dfujim/bccd
Author: Derek Fujimoto
Author-email: fujimoto@phas.ubc.ca
License: UNKNOWN
Platform: UNKNOWN
Classifier: Programming Language :: Python :: 3
Classifier: Programming Language :: Python :: 3.6
Classifier: Programming Language :: Python :: 3.7
Classifier: License :: OSI Approved :: GNU Lesser General Public License v3 (LGPLv3)
Classifier: Operating System :: POSIX :: Linux
